README.md
setup.py
fmri_delay/__init__.py
fmri_delay/delay.py
fmri_delay/innovation.py
fmri_delay/istarmap.py
fmri_delay/synthetic.py
fmri_delay/validation.py
fmri_delay.egg-info/PKG-INFO
fmri_delay.egg-info/SOURCES.txt
fmri_delay.egg-info/dependency_links.txt
fmri_delay.egg-info/not-zip-safe
fmri_delay.egg-info/requires.txt
fmri_delay.egg-info/top_level.txt